stage1/devision_16bits_int_seq/src/led_encoder_board.v
/**
 * Copyright © 2024 Bai Jiale 578767478@qq.com
 * License: MIT
 */

// module led_encoder(in, out, out2, out3, out4, led_in, led_out);
module led_encoder(in, out, led1, led2, led3, led4);
    input wire[15:0] in;
    output reg[6:0] out;
    output reg led1;
    output reg led2;
    output reg led3;
    output reg led4;

    initial begin
        led1 = 1'b0;
        led2 = 1'b0;
        led3 = 1'b0;
        led4 = 1'b0;
    end

    always@(in) begin
        led1 = 1'b1; led2 = 1'b0; led3 = 1'b0; led4 = 1'b0;
        case(in[3:0])
            4'b0000: out = 7'b0111111; // 0
            4'b0001: out = 7'b0000110; // 1
            4'b0010: out = 7'b1011011; // 2
            4'b0011: out = 7'b1001111; // 3
            4'b0100: out = 7'b1100110; // 4
            4'b0101: out = 7'b1101101; // 5
            4'b0110: out = 7'b1111101; // 6
            4'b0111: out = 7'b0000111; // 7
            4'b1000: out = 7'b1111111; // 8
            4'b1001: out = 7'b1101111; // 9
            4'b1010: out = 7'b1110111; // A
            4'b1011: out = 7'b1111100; // b
            4'b1100: out = 7'b0111001; // C
            4'b1101: out = 7'b1011110; // d
            4'b1110: out = 7'b1111001; // E
            4'b1111: out = 7'b1110001; // F
        endcase
        #10

        led1 = 1'b0; led2 = 1'b1; led3 = 1'b0; led4 = 1'b0;
        case(in[7:4])
            4'b0000: out = 7'b0111111; // 0
            4'b0001: out = 7'b0000110; // 1
            4'b0010: out = 7'b1011011; // 2
            4'b0011: out = 7'b1001111; // 3
            4'b0100: out = 7'b1100110; // 4
            4'b0101: out = 7'b1101101; // 5
            4'b0110: out = 7'b1111101; // 6
            4'b0111: out = 7'b0000111; // 7
            4'b1000: out = 7'b1111111; // 8
            4'b1001: out = 7'b1101111; // 9
            4'b1010: out = 7'b1110111; // A
            4'b1011: out = 7'b1111100; // b
            4'b1100: out = 7'b0111001; // C
            4'b1101: out = 7'b1011110; // d
            4'b1110: out = 7'b1111001; // E
            4'b1111: out = 7'b1110001; // F
        endcase
        #10

        led1 = 1'b0; led2 = 1'b0; led3 = 1'b1; led4 = 1'b0;
        case(in[11:8])
            4'b0000: out = 7'b0111111; // 0
            4'b0001: out = 7'b0000110; // 1
            4'b0010: out = 7'b1011011; // 2
            4'b0011: out = 7'b1001111; // 3
            4'b0100: out = 7'b1100110; // 4
            4'b0101: out = 7'b1101101; // 5
            4'b0110: out = 7'b1111101; // 6
            4'b0111: out = 7'b0000111; // 7
            4'b1000: out = 7'b1111111; // 8
            4'b1001: out = 7'b1101111; // 9
            4'b1010: out = 7'b1110111; // A
            4'b1011: out = 7'b1111100; // b
            4'b1100: out = 7'b0111001; // C
            4'b1101: out = 7'b1011110; // d
            4'b1110: out = 7'b1111001; // E
            4'b1111: out = 7'b1110001; // F
        endcase
        #10

        led1 = 1'b0; led2 = 1'b0; led3 = 1'b0; led4 = 1'b1;
        case(in[15:12])
            4'b0000: out = 7'b0111111; // 0
            4'b0001: out = 7'b0000110; // 1
            4'b0010: out = 7'b1011011; // 2
            4'b0011: out = 7'b1001111; // 3
            4'b0100: out = 7'b1100110; // 4
            4'b0101: out = 7'b1101101; // 5
            4'b0110: out = 7'b1111101; // 6
            4'b0111: out = 7'b0000111; // 7
            4'b1000: out = 7'b1111111; // 8
            4'b1001: out = 7'b1101111; // 9
            4'b1010: out = 7'b1110111; // A
            4'b1011: out = 7'b1111100; // b
            4'b1100: out = 7'b0111001; // C
            4'b1101: out = 7'b1011110; // d
            4'b1110: out = 7'b1111001; // E
            4'b1111: out = 7'b1110001; // F
        endcase
    end
endmodule

stage1/devision_16bits_int_seq/src/devision_seq_board.v
/**
 * 16bits int devision with sequential logic
 * 
 * Copyright © 2024 Bai Jiale 578767478@qq.com
 * License: MIT
 */
module devision_seq_board(clk, rst, start, done, a, b, y, remainder);
    parameter WIDTH = 16;

    input wire clk;
    input wire rst; // 重置信号，初始化寄存器
    input wire start; // 开始信号
    output reg done;

    input wire[WIDTH-1:0] a;
    input wire[WIDTH-1:0] b;
    output reg[WIDTH-1:0] y;
    output reg[WIDTH-1:0] remainder;

    reg[2*WIDTH-1:0] Ra; // 存储被除数和余数
    reg[WIDTH-1:0] Rb; // 存储除数
    reg[WIDTH-1:0] Rc; // 存储商
    reg[5:0] count; // 计数器，用于控制移位次数（最多16次）
    reg[1:0] state; // 0 表示空闲；1 表示运行中；2 表示已完成

    initial begin
        state = 1'b0;
        done = 1'b0;
    end

    always@(posedge clk or posedge rst) begin
        if (rst) begin
            state <= 0;
            done <= 0;
            y <= 0;
            remainder <= 0;
        end
        else begin
            case (state)
                0: begin
                    count <= 16;
                    if (start) begin
                        Ra = {16'h0000, a};
                        Rb = b;
                        Rc = 16'h0000;
                        state <= 1;
                    end
                end

                1: begin
                    if (count != 0) begin
                        Ra = Ra << 1;
                        Rc = Rc << 1;

                        if (Ra[31:16] >= Rb) begin
                            Ra[31:16] = Ra[31:16] - Rb;
                            Rc[0] = 1;
                        end
                        else begin
                            Rc[0] = 0;
                        end
                        count <= count - 1;
                    end
                    else begin
                        y = Rc;
                        remainder = Ra[31:16];
                        state <= 2;
                    end
                end

                2: begin
                    done <= 1;
                    state <= 0;
                end
            endcase
        end
    end
endmodule

stage1/devision_16bits_int_seq/test/devision_seq_board_tb.v
/**
 * Copyright © 2024 Bai Jiale 578767478@qq.com
 * License: MIT
 */
`timescale 1ns/1ns

module devision_seq_board_tb();
    reg clk;
    reg rst;
    reg start;
    wire done;
    reg[15:0] a;
    reg[15:0] b;
    wire[15:0] y;
    wire[15:0] remainder;
    wire[6:0] out;
    wire led1;
    wire led2;
    wire led3;
    wire led4;

    devision_seq_board uut(
        .clk        (clk),
        .rst        (rst),
        .done       (done),
        .start      (start),
        .a          (a),
        .b          (b),
        .y          (y),
        .remainder  (remainder)
    );

    led_encoder uut_led(
        .in         (y),
        .out       (out),
        .led1       (led1),
        .led2       (led2),
        .led3       (led3),
        .led4       (led4)
    );

    initial begin
        $dumpfile("wave.vcd");
        $dumpvars(0, devision_seq_board_tb);

        clk = 0;
        rst = 0;
        start = 0;

        a = 16'h0000;
        b = 16'h0000;
    end

    always begin
        #5 clk = ~clk; //* T = 10ns
    end

    initial begin
        // Test case 1 ---------------------------
        rst = 1; #10; rst = 0;

        a = 16'd110;
        b = 16'd25;

        start = 1; #10 start = 0;

        wait(done);
        #50

        // Test case 2 ----------------------------
        rst = 1; #10 rst = 0;

        a = 16'd32200;
        b = 16'd37;

        start = 1; #10 start = 0;
        
        wait(done);
        #50;

        // Test case 3 -----------------------------
        rst = 1; #10 rst = 0;

        a = 16'd1234;
        b = 16'd56;

        start = 1; #10 start = 0;

        wait(done);
        #50;

        $finish;
    end
endmodule

stage1/devision_16bits_int_seq/wave.vcd
$date
	Fri Nov  8 22:41:38 2024
$end
$version
	Icarus Verilog
$end
$timescale
	1ns
$end
$scope module devision_seq_board_tb $end
$var wire 16 ! y [15:0] $end
$var wire 16 " remainder [15:0] $end
$var wire 7 # out [6:0] $end
$var wire 1 $ led4 $end
$var wire 1 % led3 $end
$var wire 1 & led2 $end
$var wire 1 ' led1 $end
$var wire 1 ( done $end
$var reg 16 ) a [15:0] $end
$var reg 16 * b [15:0] $end
$var reg 1 + clk $end
$var reg 1 , rst $end
$var reg 1 - start $end
$scope module uut $end
$var wire 16 . a [15:0] $end
$var wire 16 / b [15:0] $end
$var wire 1 + clk $end
$var wire 1 , rst $end
$var wire 1 - start $end
$var parameter 32 0 WIDTH $end
$var reg 32 1 Ra [31:0] $end
$var reg 16 2 Rb [15:0] $end
$var reg 16 3 Rc [15:0] $end
$var reg 6 4 count [5:0] $end
$var reg 1 ( done $end
$var reg 16 5 remainder [15:0] $end
$var reg 2 6 state [1:0] $end
$var reg 16 7 y [15:0] $end
$upscope $end
$scope module uut_led $end
$var wire 16 8 in [15:0] $end
$var reg 1 ' led1 $end
$var reg 1 & led2 $end
$var reg 1 % led3 $end
$var reg 1 $ led4 $end
$var reg 7 9 out [6:0] $end
$upscope $end
$upscope $end
$enddefinitions $end
$comment Show the parameter values. $end
$dumpall
b10000 0
$end
#0
$dumpvars
b111111 9
b0 8
b0 7
b0 6
b0 5
bx 4
bx 3
bx 2
bx 1
b0 /
b0 .
0-
1,
0+
b0 *
b0 )
0(
1'
0&
0%
0$
b111111 #
b0 "
b0 !
$end
#5
1+
#10
0+
1&
0'
1-
b11001 *
b11001 /
b1101110 )
b1101110 .
0,
#15
b1 6
b10000 4
b0 3
b11001 2
b1101110 1
1+
#20
0+
1%
0&
0-
#25
b1111 4
b11011100 1
1+
#30
0+
1$
0%
#35
b1110 4
b110111000 1
1+
#40
0+
#45
b1101 4
b1101110000 1
1+
#50
0+
#55
b1100 4
b11011100000 1
1+
#60
0+
#65
b1011 4
b110111000000 1
1+
#70
0+
#75
b1010 4
b1101110000000 1
1+
#80
0+
#85
b1001 4
b11011100000000 1
1+
#90
0+
#95
b1000 4
b110111000000000 1
1+
#100
0+
#105
b111 4
b1101110000000000 1
1+
#110
0+
#115
b110 4
b11011100000000000 1
1+
#120
0+
#125
b101 4
b110111000000000000 1
1+
#130
0+
#135
b100 4
b1101110000000000000 1
1+
#140
0+
#145
b11 4
b11011100000000000000 1
1+
#150
0+
#155
b10 4
b1 3
b101000000000000000 1
1+
#160
0+
#165
b1 4
b10 3
b1010000000000000000 1
1+
#170
0+
#175
b0 4
b100 3
b10100000000000000000 1
1+
#180
0+
#185
b10 6
b1100110 #
b1100110 9
0$
1'
b1010 "
b1010 5
b100 !
b100 7
b100 8
1+
#190
0+
#195
b0 6
1(
1+
b111111 #
b111111 9
1&
0'
#200
0+
#205
b10000 4
1+
1%
0&
#210
0+
#215
1+
1$
0%
#220
0+
#225
1+
#230
0+
#235
1+
#240
0+
#245
0$
1'
b0 "
b0 5
b0 !
b0 7
b0 8
0(
1+
1,
#250
0+
#255
b1 6
b0 3
b100101 2
b111110111001000 1
1+
1&
0'
1-
b100101 *
b100101 /
b111110111001000 )
b111110111001000 .
0,
#260
0+
#265
b1111 4
b1111101110010000 1
1+
1%
0&
0-
#270
0+
#275
b1110 4
b11111011100100000 1
1+
1$
0%
#280
0+
#285
b1101 4
b111110111001000000 1
1+
#290
0+
#295
b1100 4
b1111101110010000000 1
1+
#300
0+
#305
b1011 4
b11111011100100000000 1
1+
#310
0+
#315
b1010 4
b111110111001000000000 1
1+
#320
0+
#325
b1001 4
b1 3
b110011110010000000000 1
1+
#330
0+
#335
b1000 4
b11 3
b11101100100000000000 1
1+
#340
0+
#345
b111 4
b110 3
b111011001000000000000 1
1+
#350
0+
#355
b110 4
b1101 3
b101100010000000000000 1
1+
#360
0+
#365
b101 4
b11011 3
b1110100000000000000 1
1+
#370
0+
#375
b100 4
b110110 3
b11101000000000000000 1
1+
#380
0+
#385
b11 4
b1101100 3
b111010000000000000000 1
1+
#390
0+
#395
b10 4
b11011001 3
b101010000000000000000 1
1+
#400
0+
#405
b1 4
b110110011 3
b1010000000000000000 1
1+
#410
0+
#415
b0 4
b1101100110 3
b10100000000000000000 1
1+
#420
0+
#425
b10 6
b1111101 #
b1111101 9
0$
1'
b1010 "
b1010 5
b1101100110 !
b1101100110 7
b1101100110 8
1+
#430
0+
#435
b0 6
1(
1+
1&
0'
#440
0+
#445
b10000 4
1+
b1001111 #
b1001111 9
1%
0&
#450
0+
#455
1+
b111111 #
b111111 9
1$
0%
#460
0+
#465
1+
#470
0+
#475
1+
#480
0+
#485
0$
1'
b0 "
b0 5
b0 !
b0 7
b0 8
0(
1+
1,
#490
0+
#495
b1 6
b0 3
b111000 2
b10011010010 1
1+
1&
0'
1-
b111000 *
b111000 /
b10011010010 )
b10011010010 .
0,
#500
0+
#505
b1111 4
b100110100100 1
1+
1%
0&
0-
#510
0+
#515
b1110 4
b1001101001000 1
1+
1$
0%
#520
0+
#525
b1101 4
b10011010010000 1
1+
#530
0+
#535
b1100 4
b100110100100000 1
1+
#540
0+
#545
b1011 4
b1001101001000000 1
1+
#550
0+
#555
b1010 4
b10011010010000000 1
1+
#560
0+
#565
b1001 4
b100110100100000000 1
1+
#570
0+
#575
b1000 4
b1001101001000000000 1
1+
#580
0+
#585
b111 4
b10011010010000000000 1
1+
#590
0+
#595
b110 4
b100110100100000000000 1
1+
#600
0+
#605
b101 4
b1001101001000000000000 1
1+
#610
0+
#615
b100 4
b1 3
b101010010000000000000 1
1+
#620
0+
#625
b11 4
b10 3
b1010100100000000000000 1
1+
#630
0+
#635
b10 4
b101 3
b111001000000000000000 1
1+
#640
0+
#645
b1 4
b1011 3
b10000000000000000 1
1+
#650
0+
#655
b0 4
b10110 3
b100000000000000000 1
1+
#660
0+
#665
b10 6
b1111101 #
b1111101 9
0$
1'
b10 "
b10 5
b10110 !
b10110 7
b10110 8
1+
#670
0+
#675
b0 6
1(
1+
b110 #
b110 9
1&
0'
#680
0+
#685
b10000 4
1+
b111111 #
b111111 9
1%
0&
#690
0+
#695
1+
1$
0%
