stage1/devision_16bits_int_seq/src/devision_seq_led_board.v
/**
 * 16bits int devision with sequential logic
 * 
 * Copyright © 2024 Bai Jiale 578767478@qq.com
 * License: MIT
 */
module devision_seq_led_board(clk, rst, start, done, led1, led2, led3, led4, out);
    parameter WIDTH = 16;

    input wire clk;
    input wire rst; // 重置信号，初始化寄存器
    input wire start; // 开始信号
    output reg done;
    output reg led1;
    output reg led2;
    output reg led3;
    output reg led4;
    output reg[6:0] out;

    reg[WIDTH-1:0] a;
    reg[WIDTH-1:0] b;
    reg[WIDTH-1:0] y;
    reg[WIDTH-1:0] remainder;
    reg[2*WIDTH-1:0] Ra; // 存储被除数和余数
    reg[WIDTH-1:0] Rb; // 存储除数
    reg[WIDTH-1:0] Rc; // 存储商
    reg[5:0] count; // 计数器，用于控制移位次数（最多16次）
    reg[1:0] state; // 0 表示空闲；1 表示运行中；2 表示已完成

    initial begin
        state = 1'b0;
        done = 1'b0;
        a = 16'd32200;
        b = 16'd37;
        led1 = 1'b0;
        led2 = 1'b0;
        led3 = 1'b0;
        led4 = 1'b0;
    end

    always@(posedge clk or posedge rst) begin
        if (rst) begin
            state <= 0;
            done <= 0;
            y <= 0;
            remainder <= 0;
        end
        else begin
            case (state)
                0: begin
                    count <= 16;
                    if (start) begin
                        Ra = {16'h0000, a};
                        Rb = b;
                        Rc = 16'h0000;
                        state <= 1;
                    end
                end

                1: begin
                    if (count != 0) begin
                        Ra = Ra << 1;
                        Rc = Rc << 1;

                        if (Ra[31:16] >= Rb) begin
                            Ra[31:16] = Ra[31:16] - Rb;
                            Rc[0] = 1;
                        end
                        else begin
                            Rc[0] = 0;
                        end
                        count <= count - 1;
                    end
                    else begin
                        y = Rc;
                        remainder = Ra[31:16];
                        state <= 2;
                    end
                end

                2: begin
                    done <= 1;
                    state <= 0;
                end
            endcase
        end
    end

    always@(y) begin
        led1 = 1'b1; led2 = 1'b0; led3 = 1'b0; led4 = 1'b0;
        case(y[3:0])
            4'b0000: out = 7'b0111111; // 0
            4'b0001: out = 7'b0000110; // 1
            4'b0010: out = 7'b1011011; // 2
            4'b0011: out = 7'b1001111; // 3
            4'b0100: out = 7'b1100110; // 4
            4'b0101: out = 7'b1101101; // 5
            4'b0110: out = 7'b1111101; // 6
            4'b0111: out = 7'b0000111; // 7
            4'b1000: out = 7'b1111111; // 8
            4'b1001: out = 7'b1101111; // 9
            4'b1010: out = 7'b1110111; // A
            4'b1011: out = 7'b1111100; // b
            4'b1100: out = 7'b0111001; // C
            4'b1101: out = 7'b1011110; // d
            4'b1110: out = 7'b1111001; // E
            4'b1111: out = 7'b1110001; // F
        endcase
        #10

        led1 = 1'b0; led2 = 1'b1; led3 = 1'b0; led4 = 1'b0;
        case(y[7:4])
            4'b0000: out = 7'b0111111; // 0
            4'b0001: out = 7'b0000110; // 1
            4'b0010: out = 7'b1011011; // 2
            4'b0011: out = 7'b1001111; // 3
            4'b0100: out = 7'b1100110; // 4
            4'b0101: out = 7'b1101101; // 5
            4'b0110: out = 7'b1111101; // 6
            4'b0111: out = 7'b0000111; // 7
            4'b1000: out = 7'b1111111; // 8
            4'b1001: out = 7'b1101111; // 9
            4'b1010: out = 7'b1110111; // A
            4'b1011: out = 7'b1111100; // b
            4'b1100: out = 7'b0111001; // C
            4'b1101: out = 7'b1011110; // d
            4'b1110: out = 7'b1111001; // E
            4'b1111: out = 7'b1110001; // F
        endcase
        #10

        led1 = 1'b0; led2 = 1'b0; led3 = 1'b1; led4 = 1'b0;
        case(y[11:8])
            4'b0000: out = 7'b0111111; // 0
            4'b0001: out = 7'b0000110; // 1
            4'b0010: out = 7'b1011011; // 2
            4'b0011: out = 7'b1001111; // 3
            4'b0100: out = 7'b1100110; // 4
            4'b0101: out = 7'b1101101; // 5
            4'b0110: out = 7'b1111101; // 6
            4'b0111: out = 7'b0000111; // 7
            4'b1000: out = 7'b1111111; // 8
            4'b1001: out = 7'b1101111; // 9
            4'b1010: out = 7'b1110111; // A
            4'b1011: out = 7'b1111100; // b
            4'b1100: out = 7'b0111001; // C
            4'b1101: out = 7'b1011110; // d
            4'b1110: out = 7'b1111001; // E
            4'b1111: out = 7'b1110001; // F
        endcase
        #10

        led1 = 1'b0; led2 = 1'b0; led3 = 1'b0; led4 = 1'b1;
        case(y[15:12])
            4'b0000: out = 7'b0111111; // 0
            4'b0001: out = 7'b0000110; // 1
            4'b0010: out = 7'b1011011; // 2
            4'b0011: out = 7'b1001111; // 3
            4'b0100: out = 7'b1100110; // 4
            4'b0101: out = 7'b1101101; // 5
            4'b0110: out = 7'b1111101; // 6
            4'b0111: out = 7'b0000111; // 7
            4'b1000: out = 7'b1111111; // 8
            4'b1001: out = 7'b1101111; // 9
            4'b1010: out = 7'b1110111; // A
            4'b1011: out = 7'b1111100; // b
            4'b1100: out = 7'b0111001; // C
            4'b1101: out = 7'b1011110; // d
            4'b1110: out = 7'b1111001; // E
            4'b1111: out = 7'b1110001; // F
        endcase
    end
endmodule

stage1/devision_16bits_int_seq/test/devision_seq_led_board_tb.v
`timescale 1ns / 1ps

module devision_seq_led_board_tb();
    // 参数定义
    parameter WIDTH = 16;

    // 输入信号
    reg clk;
    reg rst;
    reg start;

    // 输出信号
    wire done;
    wire led1;
    wire led2;
    wire led3;
    wire led4;
    wire [6:0] out;

    // 实例化被测试模块
    devision_seq_led_board uut (
        .clk(clk),
        .rst(rst),
        .start(start),
        .done(done),
        .out(out),
        .led1(led1),
        .led2(led2),
        .led3(led3),
        .led4(led4)
    );

    // 时钟生成
    initial begin
        $dumpfile("wave.vcd");
        $dumpvars(0, devision_seq_led_board_tb);
        clk = 0;
        forever #5 clk = ~clk; // 10ns周期的时钟
    end

    // 初始化输入信号
    initial begin
        // 初始化信号
        rst = 1;
        start = 0;

        // 监视信号变化
        $monitor("time=%0d, rst=%b, start=%b, done=%b, led1=%b, led2=%b, led3=%b, led4=%b", 
                 $time, rst, start, done, led1, led2, led3, led4);

        // 复位信号
        #10 rst = 0;
        #10 rst = 1;
        #10 rst = 0;

        // 开始信号
        #20 start = 1;
        #10 start = 0;

        // 等待计算完成
        wait(done);

        // 结束仿真
        #100 $finish;
    end

endmodule

stage1/devision_16bits_int_seq/wave.vcd
$date
	Sat Nov  9 16:07:43 2024
$end
$version
	Icarus Verilog
$end
$timescale
	1ps
$end
$scope module devision_seq_led_board_tb $end
$var wire 7 ! out [6:0] $end
$var wire 1 " led4 $end
$var wire 1 # led3 $end
$var wire 1 $ led2 $end
$var wire 1 % led1 $end
$var wire 1 & done $end
$var parameter 32 ' WIDTH $end
$var reg 1 ( clk $end
$var reg 1 ) rst $end
$var reg 1 * start $end
$scope module uut $end
$var wire 1 ( clk $end
$var wire 1 ) rst $end
$var wire 1 * start $end
$var parameter 32 + WIDTH $end
$var reg 32 , Ra [31:0] $end
$var reg 16 - Rb [15:0] $end
$var reg 16 . Rc [15:0] $end
$var reg 16 / a [15:0] $end
$var reg 16 0 b [15:0] $end
$var reg 6 1 count [5:0] $end
$var reg 1 & done $end
$var reg 1 % led1 $end
$var reg 1 $ led2 $end
$var reg 1 # led3 $end
$var reg 1 " led4 $end
$var reg 7 2 out [6:0] $end
$var reg 16 3 remainder [15:0] $end
$var reg 2 4 state [1:0] $end
$var reg 16 5 y [15:0] $end
$upscope $end
$upscope $end
$enddefinitions $end
$comment Show the parameter values. $end
$dumpall
b10000 +
b10000 '
$end
#0
$dumpvars
b0 5
b0 4
b0 3
b111111 2
bx 1
b100101 0
b111110111001000 /
bx .
bx -
bx ,
0*
1)
0(
0&
1%
0$
0#
0"
b111111 !
$end
#5000
1(
#10000
0(
1$
0%
0)
#15000
b10000 1
1(
#20000
0(
1#
0$
1)
#25000
1(
#30000
0(
1"
0#
0)
#35000
1(
#40000
0(
#45000
1(
#50000
0(
1*
#55000
b1 4
b0 .
b100101 -
b111110111001000 ,
1(
#60000
0(
0*
#65000
b1111 1
b1111101110010000 ,
1(
#70000
0(
#75000
b1110 1
b11111011100100000 ,
1(
#80000
0(
#85000
b1101 1
b111110111001000000 ,
1(
#90000
0(
#95000
b1100 1
b1111101110010000000 ,
1(
#100000
0(
#105000
b1011 1
b11111011100100000000 ,
1(
#110000
0(
#115000
b1010 1
b111110111001000000000 ,
1(
#120000
0(
#125000
b1001 1
b1 .
b110011110010000000000 ,
1(
#130000
0(
#135000
b1000 1
b11 .
b11101100100000000000 ,
1(
#140000
0(
#145000
b111 1
b110 .
b111011001000000000000 ,
1(
#150000
0(
#155000
b110 1
b1101 .
b101100010000000000000 ,
1(
#160000
0(
#165000
b101 1
b11011 .
b1110100000000000000 ,
1(
#170000
0(
#175000
b100 1
b110110 .
b11101000000000000000 ,
1(
#180000
0(
#185000
b11 1
b1101100 .
b111010000000000000000 ,
1(
#190000
0(
#195000
b10 1
b11011001 .
b101010000000000000000 ,
1(
#200000
0(
#205000
b1 1
b110110011 .
b1010000000000000000 ,
1(
#210000
0(
#215000
b0 1
b1101100110 .
b10100000000000000000 ,
1(
#220000
0(
#225000
b10 4
b1111101 !
b1111101 2
0"
1%
b1010 3
b1101100110 5
1(
#230000
0(
#235000
b0 4
1&
1(
1$
0%
#240000
0(
#245000
b10000 1
1(
b1001111 !
b1001111 2
1#
0$
#250000
0(
#255000
1(
b111111 !
b111111 2
1"
0#
