stage1/task1_decoder_3_8/src/decoder_3_8.v
module decoder_3_8(a, b, c, out);
    input a,b,c;  //端口定义
    output reg [7:0] out;//对out定义为1个8位的数据
    //always块描述的信号赋值，被赋值对象必须定义为reg
    // reg [7:0] out; //定义out为1个8位的寄存器

    always @(*) begin
        out[0] = !a && !b && !c;
        out[1] = !a && !b && c;
        out[2] = !a && b && !c;
        out[3] = !a && b && c;
        out[4] = a && !b && !c;
        out[5] = a && !b && c;
        out[6] = a && b && !c;
        out[7] = a && b && c;
        //一个等价的写法是always @(a, b, c),其中的*表示通配符
        //always表示一个语法块
        // case ({a,b,c}) //里面的大括号内容：{a,b.c}表示一个3位的信号这种操作叫做拼接
        //     3'b000: out = 8'b0000_0001;  //b表示binary 二进制，3'b000，表示一个3位的二进制信号，值为000
        //     3'b001: out = 8'b00000010;  //还有常用的格式，比如 d是十进制，3'd5，表示一个3位的十进制信号，值为5和3'b101完全等价
        //     3'b010: out = 8'b00000100;  //h是十六进制 
        //     3'b011: out = 8'b00001000;   //o是八进制符号
        //     3'b100: out = 8'b00010000;
        //     3'b101: out = 8'b00100000;
        //     3'b110: out = 8'b01000000;
        //     3'b111: out = 8'b10000000;
        // endcase
    end
    //一个拼接的例子
    //wire [3:0]d;
    //assign d = {a,1'b0,b,c};
    //拼接了一个四位的信号，其中第一位是a，第二位是0，第三位是b，第四位是c
endmodule

stage1/task1_decoder_3_8/test/decoder_3_8_tb.v
`timescale 1ns/1ns //第一个是时间单位，第二个是时间精度
`include "/Users/baijiale/Documents/Code/fpga-design-uestc/stage1/task1_decoder_3_8/mod/decoder_3_8.v"

module decoder_3_8_tb; //由于这是仿真文件所以不需要写模块端口号
    //开始例化
    reg s_a,s_b,s_c; //定义s_a,s_b,s_c为reg信号
    wire [7:0] s_out; //定义s_out为wire信号

    decoder_3_8 decoder_3_8(
        .a      (s_a),
        .b      (s_b), //这里的s_a,s_b,s_c,s_out都是仿真文件中的信号
        .c      (s_c), //a,b,c都是激励信号，都要设计成reg信号
        .out    (s_out) //out是要被观测的信号，定义成wire类型
    );

    //结束例化
    //开始产生激励
    initial begin
        s_a = 0; s_b = 0; s_c = 0; //初始化信号
        #200 s_a = 0; s_b = 0; s_c = 1; //200ns后，s_a = 0; s_b = 0; s_c = 1;
        #200 s_a = 0; s_b = 1; s_c = 0; //200ns后，s_a = 0; s_b = 1; s_c = 0;
        #200 s_a = 0; s_b = 1; s_c = 1; //200ns后，s_a = 0; s_b = 1; s_c = 1;
        #200 s_a = 1; s_b = 0; s_c = 0; //200ns后，s_a = 1; s_b = 0; s_c = 0;
        #200 s_a = 1; s_b = 0; s_c = 1; //200ns后，s_a = 1; s_b = 0; s_c = 1;
        #200 s_a = 1; s_b = 1; s_c = 0; //200ns后，s_a = 1; s_b = 1; s_c = 0;
        #200 s_a = 1; s_b = 1; s_c = 1; //200ns后，s_a = 1; s_b = 1; s_c = 1;
        #2000 $finish;
    end

    initial begin
        $dumpfile("wave.vcd");
        $dumpvars(0, decoder_3_8_tb);	// tb的模块名
    end
endmodule

stage1/decoder_3_8/wave.vcd
$date
	Sat Nov 16 16:21:13 2024
$end
$version
	Icarus Verilog
$end
$timescale
	1ns
$end
$scope module decoder_3_8_tb $end
$var wire 8 ! s_out [7:0] $end
$var reg 1 " s_a $end
$var reg 1 # s_b $end
$var reg 1 $ s_c $end
$scope module decoder_3_8 $end
$var wire 1 " a $end
$var wire 1 # b $end
$var wire 1 $ c $end
$var reg 8 % out [7:0] $end
$upscope $end
$upscope $end
$enddefinitions $end
$comment Show the parameter values. $end
$dumpall
$end
#0
$dumpvars
b1 %
0$
0#
0"
b1 !
$end
#200
b10 !
b10 %
1$
#400
b100 !
b100 %
0$
1#
#600
b1000 !
b1000 %
1$
#800
b10000 !
b10000 %
0$
0#
1"
#1000
b100000 !
b100000 %
1$
#1200
b1000000 !
b1000000 %
0$
1#
#1400
b10000000 !
b10000000 %
1$
