stage1/task1_water_led/src/water_led.v
module water_led(clock, reset, led_out);
    parameter CNT_MAX = 32'd100;
    parameter HIGH_LEVEL = 1'b1;
    parameter LOW_LEVEL = 1'b0;

    input wire clock; // clock，board f = 100MHz
    input wire reset; // reset，**if High-Level Reset**

    output reg [3:0] led_out; // output

    reg [31:0] counter; // 32 bit counter
    reg has_count_500ms;

    initial begin
        led_out = 4'b0000;
        counter = 32'd0;
        has_count_500ms = 1'b0;
    end

    // count 0.5s
    always@(posedge clock) begin 
        if (reset == 1'b1) begin // if reset do:
            counter <= 32'd0;
            has_count_500ms <= 1'b0;
        end
        else if (counter == CNT_MAX) begin
            counter <= 32'd0;
            has_count_500ms <= 1'b1;
        end
        else begin
            counter <= counter + 1'b1;
        end
    end

    always@(posedge clock) begin
        if (reset == HIGH_LEVEL) begin //? 为什么一开始一定要先打开 reset
            led_out <= 4'b0001; // 复位时LED初始化
        end
        else if (has_count_500ms == 1'b1) begin
            if (led_out == 4'b1000) begin
                led_out <= 4'b0001; // 如果LED移到最左边，则回到最右边
            end
            else begin
                led_out <= led_out << 1; // 否则LED向左移一位
            end
            has_count_500ms <= 1'b0;
        end
    end
endmodule

stage1/task1_water_led/test/water_led_tb.v
// tb文件本身没有输入输出，为的是调用源文件的功能进而测试它
`timescale 1ns/1ns

module water_led_tb();
    reg clk;
    reg rst;
    wire[3:0] lout;

    // 例化
    water_led water_led(
        .clock      (clk),
        .reset      (rst),
        .led_out    (lout)
    );

    initial begin
        $dumpfile("wave.vcd");
        $dumpvars(0, water_led_tb);

        clk = 1'b1;
        rst = 1'b1;  // 初始化复位为高电平 //? 为什么初始化是一定要 reset 为真
        #50 rst = 1'b0;  // 50ns后释放复位

        #1000 rst = 1'b1;
        #500 rst = 1'b0;
        #20000 $finish;
    end

    always begin
        #5 clk = ~clk; // f = 100MHz, T = 10ns
    end

endmodule

stage1/task1_water_led/wave.vcd
$date
	Sat Oct 19 15:49:23 2024
$end
$version
	Icarus Verilog
$end
$timescale
	1ns
$end
$scope module water_led_tb $end
$var wire 4 ! lout [3:0] $end
$var reg 1 " clk $end
$var reg 1 # rst $end
$scope module water_led $end
$var wire 1 " clock $end
$var wire 1 # reset $end
$var parameter 32 $ CNT_MAX $end
$var parameter 1 % HIGH_LEVEL $end
$var parameter 1 & LOW_LEVEL $end
$var reg 32 ' counter [31:0] $end
$var reg 1 ( has_count_500ms $end
$var reg 4 ) led_out [3:0] $end
$upscope $end
$upscope $end
$enddefinitions $end
$comment Show the parameter values. $end
$dumpall
0&
1%
b1100100 $
$end
#0
$dumpvars
b1 )
0(
b0 '
1#
1"
b1 !
$end
#5
0"
#10
1"
#15
0"
#20
1"
#25
0"
#30
1"
#35
0"
#40
1"
#45
0"
#50
b1 '
1"
0#
#55
0"
#60
b10 '
1"
#65
0"
#70
b11 '
1"
#75
0"
#80
b100 '
1"
#85
0"
#90
b101 '
1"
#95
0"
#100
b110 '
1"
#105
0"
#110
b111 '
1"
#115
0"
#120
b1000 '
1"
#125
0"
#130
b1001 '
1"
#135
0"
#140
b1010 '
1"
#145
0"
#150
b1011 '
1"
#155
0"
#160
b1100 '
1"
#165
0"
#170
b1101 '
1"
#175
0"
#180
b1110 '
1"
#185
0"
#190
b1111 '
1"
#195
0"
#200
b10000 '
1"
#205
0"
#210
b10001 '
1"
#215
0"
#220
b10010 '
1"
#225
0"
#230
b10011 '
1"
#235
0"
#240
b10100 '
1"
#245
0"
#250
b10101 '
1"
#255
0"
#260
b10110 '
1"
#265
0"
#270
b10111 '
1"
#275
0"
#280
b11000 '
1"
#285
0"
#290
b11001 '
1"
#295
0"
#300
b11010 '
1"
#305
0"
#310
b11011 '
1"
#315
0"
#320
b11100 '
1"
#325
0"
#330
b11101 '
1"
#335
0"
#340
b11110 '
1"
#345
0"
#350
b11111 '
1"
#355
0"
#360
b100000 '
1"
#365
0"
#370
b100001 '
1"
#375
0"
#380
b100010 '
1"
#385
0"
#390
b100011 '
1"
#395
0"
#400
b100100 '
1"
#405
0"
#410
b100101 '
1"
#415
0"
#420
b100110 '
1"
#425
0"
#430
b100111 '
1"
#435
0"
#440
b101000 '
1"
#445
0"
#450
b101001 '
1"
#455
0"
#460
b101010 '
1"
#465
0"
#470
b101011 '
1"
#475
0"
#480
b101100 '
1"
#485
0"
#490
b101101 '
1"
#495
0"
#500
b101110 '
1"
#505
0"
#510
b101111 '
1"
#515
0"
#520
b110000 '
1"
#525
0"
#530
b110001 '
1"
#535
0"
#540
b110010 '
1"
#545
0"
#550
b110011 '
1"
#555
0"
#560
b110100 '
1"
#565
0"
#570
b110101 '
1"
#575
0"
#580
b110110 '
1"
#585
0"
#590
b110111 '
1"
#595
0"
#600
b111000 '
1"
#605
0"
#610
b111001 '
1"
#615
0"
#620
b111010 '
1"
#625
0"
#630
b111011 '
1"
#635
0"
#640
b111100 '
1"
#645
0"
#650
b111101 '
1"
#655
0"
#660
b111110 '
1"
#665
0"
#670
b111111 '
1"
#675
0"
#680
b1000000 '
1"
#685
0"
#690
b1000001 '
1"
#695
0"
#700
b1000010 '
1"
#705
0"
#710
b1000011 '
1"
#715
0"
#720
b1000100 '
1"
#725
0"
#730
b1000101 '
1"
#735
0"
#740
b1000110 '
1"
#745
0"
#750
b1000111 '
1"
#755
0"
#760
b1001000 '
1"
#765
0"
#770
b1001001 '
1"
#775
0"
#780
b1001010 '
1"
#785
0"
#790
b1001011 '
1"
#795
0"
#800
b1001100 '
1"
#805
0"
#810
b1001101 '
1"
#815
0"
#820
b1001110 '
1"
#825
0"
#830
b1001111 '
1"
#835
0"
#840
b1010000 '
1"
#845
0"
#850
b1010001 '
1"
#855
0"
#860
b1010010 '
1"
#865
0"
#870
b1010011 '
1"
#875
0"
#880
b1010100 '
1"
#885
0"
#890
b1010101 '
1"
#895
0"
#900
b1010110 '
1"
#905
0"
#910
b1010111 '
1"
#915
0"
#920
b1011000 '
1"
#925
0"
#930
b1011001 '
1"
#935
0"
#940
b1011010 '
1"
#945
0"
#950
b1011011 '
1"
#955
0"
#960
b1011100 '
1"
#965
0"
#970
b1011101 '
1"
#975
0"
#980
b1011110 '
1"
#985
0"
#990
b1011111 '
1"
#995
0"
#1000
b1100000 '
1"
#1005
0"
#1010
b1100001 '
1"
#1015
0"
#1020
b1100010 '
1"
#1025
0"
#1030
b1100011 '
1"
#1035
0"
#1040
b1100100 '
1"
#1045
0"
#1050
b0 '
1"
1#
